pyworldpostal/__init__.py
pyworldpostal/pyinferzipcode.py
pyworldpostal/country_files/AD.py
pyworldpostal/country_files/AR.py
pyworldpostal/country_files/AS.py
pyworldpostal/country_files/AT.py
pyworldpostal/country_files/AU.py
pyworldpostal/country_files/AX.py
pyworldpostal/country_files/AZ.py
pyworldpostal/country_files/BD.py
pyworldpostal/country_files/BE.py
pyworldpostal/country_files/BG.py
pyworldpostal/country_files/BM.py
pyworldpostal/country_files/BR.py
pyworldpostal/country_files/BY.py
pyworldpostal/country_files/CA.py
pyworldpostal/country_files/CH.py
pyworldpostal/country_files/CL.py
pyworldpostal/country_files/CO.py
pyworldpostal/country_files/CR.py
pyworldpostal/country_files/CY.py
pyworldpostal/country_files/CZ.py
pyworldpostal/country_files/DE.py
pyworldpostal/country_files/DK.py
pyworldpostal/country_files/DO.py
pyworldpostal/country_files/DZ.py
pyworldpostal/country_files/EE.py
pyworldpostal/country_files/ES.py
pyworldpostal/country_files/FI.py
pyworldpostal/country_files/FM.py
pyworldpostal/country_files/FO.py
pyworldpostal/country_files/FR.py
pyworldpostal/country_files/GB.py
pyworldpostal/country_files/GF.py
pyworldpostal/country_files/GG.py
pyworldpostal/country_files/GL.py
pyworldpostal/country_files/GP.py
pyworldpostal/country_files/GT.py
pyworldpostal/country_files/GU.py
pyworldpostal/country_files/HR.py
pyworldpostal/country_files/HU.py
pyworldpostal/country_files/IE.py
pyworldpostal/country_files/IM.py
pyworldpostal/country_files/IN.py
pyworldpostal/country_files/IS.py
pyworldpostal/country_files/IT.py
pyworldpostal/country_files/JE.py
pyworldpostal/country_files/JP.py
pyworldpostal/country_files/KR.py
pyworldpostal/country_files/LI.py
pyworldpostal/country_files/LK.py
pyworldpostal/country_files/LT.py
pyworldpostal/country_files/LU.py
pyworldpostal/country_files/LV.py
pyworldpostal/country_files/MC.py
pyworldpostal/country_files/MD.py
pyworldpostal/country_files/MH.py
pyworldpostal/country_files/MK.py
pyworldpostal/country_files/MP.py
pyworldpostal-0.1.7.dist-info/LICENSE.txt
pyworldpostal-0.1.7.dist-info/METADATA
pyworldpostal-0.1.7.dist-info/WHEEL
pyworldpostal-0.1.7.dist-info/entry_points.txt
pyworldpostal-0.1.7.dist-info/top_level.txt
pyworldpostal-0.1.7.dist-info/RECORD
