Metadata-Version: 2.1
Name: pyworldpostal
Version: 0.1.7
Summary: infer geo location name using postal code
Home-page: https://github.com/dalwindr/inferzipcode.git
Download-URL: https://github.com/dalwindr/inferzipcode.git/tarball/0.1.0
Author: Dalwinder singh
Author-email: prodicus@gmail.com
License: MIT
Keywords: api,geo-location,zipcode,devtools,Development,ziptastic,latitude,longitude
Classifier: Intended Audience :: Developers
Classifier: Topic :: Software Development :: Build Tools
Classifier: License :: OSI Approved :: MIT License
Classifier: Programming Language :: Python :: 2.7
Classifier: Programming Language :: Python :: 3
Classifier: Programming Language :: Python :: 3.4
License-File: LICENSE.txt
Requires-Dist: pandas (==1.4.0)
